{
  "path": "/{apiBasePath}/<tenantId>/webauthn/signin/options",
  "method": "post",
  "description": "Get WebAuthn sign in options\n",
  "parameters": {
    "apiBasePath": {
      "name": "apiBasePath",
      "in": "path",
      "description": "Its value depends on the apiBasePath set by the user",
      "required": true,
      "schema": {
        "type": "string",
        "example": "auth"
      }
    },
    "rid": {
      "name": "rid",
      "in": "header",
      "example": "webauthn",
      "schema": {
        "type": "string"
      }
    }
  },
  "body": {},
  "responses": {
    "200": {
      "description": "WebAuthn sign in options",
      "content": {
        "application/json": {
          "schema": [
            {
              "type": "object",
              "properties": {
                "status": {
                  "type": "string",
                  "enum": [
                    "OK"
                  ]
                },
                "webauthnGeneratedOptionsId": {
                  "type": "string",
                  "example": "opt_123..."
                },
                "createdAt": {
                  "type": "string",
                  "example": "2024-03-20T10:00:00Z"
                },
                "expiresAt": {
                  "type": "string",
                  "example": "2024-03-20T10:05:00Z"
                },
                "rpId": {
                  "type": "string",
                  "example": "example.com"
                },
                "challenge": {
                  "type": "string",
                  "example": "base64challenge..."
                },
                "timeout": {
                  "type": "number",
                  "example": 300000
                },
                "userVerification": {
                  "type": "string",
                  "enum": [
                    "required",
                    "preferred",
                    "discouraged"
                  ]
                }
              }
            },
            {
              "type": "object",
              "properties": {
                "status": {
                  "type": "string",
                  "enum": [
                    "GENERAL_ERROR"
                  ]
                },
                "message": {
                  "type": "string"
                }
              }
            },
            {
              "type": "object",
              "properties": {
                "status": {
                  "type": "string",
                  "enum": [
                    "INVALID_OPTIONS_ERROR"
                  ]
                }
              }
            }
          ]
        }
      }
    },
    "404": {
      "description": "error code 404",
      "content": {
        "text/plain": {
          "schema": {
            "type": "string",
            "enum": [
              "Not Found"
            ]
          }
        }
      }
    },
    "500": {
      "description": "error code 500",
      "content": {
        "text/plain": {
          "schema": {
            "type": "string",
            "enum": [
              "Internal Error"
            ]
          }
        }
      }
    }
  }
}