{
  "path": "/appid-<appId>/<tenantId>/recipe/user/password/reset",
  "method": "post",
  "description": "Reset a password using password reset token\n",
  "parameters": {
    "rid": {
      "name": "rid",
      "in": "header",
      "example": "emailpassword",
      "required": false,
      "schema": {
        "type": "string"
      }
    },
    "Authorization": {
      "name": "Authorization",
      "in": "header",
      "example": "ajs30Nlbs0DjvsdFIne934n8NVee5n",
      "required": false,
      "schema": {
        "type": "string"
      }
    },
    "cdi-version": {
      "name": "cdi-version",
      "in": "header",
      "description": "X.Y of the X.Y.Z CDI version.",
      "example": "5.1",
      "schema": {
        "type": "string"
      }
    }
  },
  "body": {
    "schema": {
      "application/json": {
        "type": "object",
        "properties": {
          "method": {
            "type": "string",
            "enum": [
              "token"
            ]
          },
          "token": {
            "type": "string",
            "example": "ZTRiOTBjNz...jI5MTZlODkxw"
          },
          "newPassword": {
            "type": "string",
            "example": "newpassword123"
          }
        }
      }
    }
  },
  "deprecated": true,
  "responses": {
    "200": {
      "description": "Reset a password using password reset token",
      "content": {
        "application/json": {
          "schema": [
            {
              "type": "object",
              "properties": {
                "status": {
                  "type": "string",
                  "enum": [
                    "OK"
                  ]
                },
                "userId": {
                  "type": "string",
                  "example": "fa7a0841-b533-4478-95533-0fde890c3483"
                }
              }
            },
            {
              "type": "object",
              "properties": {
                "status": {
                  "type": "string",
                  "enum": [
                    "RESET_PASSWORD_INVALID_TOKEN_ERROR"
                  ]
                }
              }
            }
          ]
        }
      }
    },
    "400": {
      "description": "error code 400",
      "content": {
        "text/plain": {
          "schema": {
            "type": "string"
          }
        }
      }
    },
    "401": {
      "description": "error code 401",
      "content": {
        "text/plain": {
          "schema": {
            "type": "string",
            "enum": [
              "Invalid API key"
            ]
          }
        }
      }
    },
    "404": {
      "description": "error code 404",
      "content": {
        "text/plain": {
          "schema": {
            "type": "string",
            "enum": [
              "Not Found"
            ]
          }
        }
      }
    },
    "500": {
      "description": "error code 500",
      "content": {
        "text/plain": {
          "schema": {
            "type": "string",
            "enum": [
              "Internal Error"
            ]
          }
        }
      }
    }
  }
}